{"updatedAt":"2026-03-08T11:35:22.820Z","createdAt":"2026-01-17T17:34:57.285Z","id":"eNHx0TACVcF6MIdAYIKSl","name":"MX_00_Event_Router v2","description":null,"active":true,"isArchived":false,"nodes":[{"parameters":{"httpMethod":"POST","path":"event-router","options":{}},"id":"c8003aa5-c127-4938-bde8-a37bb758fe35","name":"Webhook Trigger","type":"n8n-nodes-base.webhook","typeVersion":2,"position":[-1616,400],"webhookId":"event-router","notes":"Receives POST from Supabase Database Webhook on INSERT to events table"},{"parameters":{"rule":{"interval":[{"field":"minutes"}]}},"id":"f6a07c43-13b1-4cf6-a26e-16b460529dd2","name":"Sweeper Trigger","type":"n8n-nodes-base.scheduleTrigger","typeVersion":1.2,"position":[-1616,624],"notes":"Runs every 5 minutes to catch missed events (Belt & Suspenders)"},{"parameters":{"jsCode":"// Transform Webhook Payload - V2 (Multi-Format Support)\n// Unterstützt: Supabase Webhook, Direct POST, curl, n8n HTTP Request\n\nconst input = $input.first().json;\nlet record = null;\nlet source = 'webhook';\n\n// ============================================\n// FORMAT 1: Supabase Database Webhook\n// Struktur: { type: 'INSERT', table: 'events', record: {...} }\n// ============================================\nif (input.type === 'INSERT' && input.record) {\n  record = input.record;\n  source = 'supabase_webhook';\n}\n\n// ============================================\n// FORMAT 2: Direct POST (curl, Postman, andere Flows)\n// Struktur: { event_id, event_type, project_id, payload }\n// ============================================\nelse if (input.event_id && input.event_type) {\n  record = {\n    id: input.event_id,\n    event_type: input.event_type,\n    project_id: input.project_id,\n    payload: input.payload || {},\n    created_at: input.created_at || new Date().toISOString(),\n    source_system: input.source_system || 'manual',\n    source_flow: input.source_flow || 'direct_post'\n  };\n  source = 'direct_post';\n}\n\n// ============================================\n// FORMAT 3: n8n Webhook Body Wrapper\n// Struktur: { body: { event_id, event_type, ... } }\n// ============================================\nelse if (input.body?.event_id && input.body?.event_type) {\n  record = {\n    id: input.body.event_id,\n    event_type: input.body.event_type,\n    project_id: input.body.project_id,\n    payload: input.body.payload || {},\n    created_at: input.body.created_at || new Date().toISOString(),\n    source_system: input.body.source_system || 'n8n',\n    source_flow: input.body.source_flow || 'webhook_body'\n  };\n  source = 'webhook_body';\n}\n\n// ============================================\n// FORMAT 4: Supabase Webhook wrapped in body\n// Struktur: { body: { type: 'INSERT', record: {...} } }\n// ============================================\nelse if (input.body?.type === 'INSERT' && input.body?.record) {\n  record = input.body.record;\n  source = 'supabase_webhook_wrapped';\n}\n\n// ============================================\n// FORMAT 5: Event-Objekt direkt (von Sweeper oder anderem Flow)\n// Struktur: { id, event_type, project_id, payload, ... }\n// ============================================\nelse if (input.id && input.event_type) {\n  record = {\n    id: input.id,\n    event_type: input.event_type,\n    project_id: input.project_id,\n    payload: input.payload || {},\n    created_at: input.created_at,\n    source_system: input.source_system,\n    source_flow: input.source_flow\n  };\n  source = 'event_object';\n}\n\n// ============================================\n// OUTPUT\n// ============================================\nif (record && record.event_type) {\n  return [{\n    json: {\n      id: record.id,\n      event_type: String(record.event_type), // Ensure string for Switch\n      project_id: record.project_id,\n      payload: typeof record.payload === 'string' \n        ? JSON.parse(record.payload) \n        : (record.payload || {}),\n      created_at: record.created_at,\n      source_system: record.source_system,\n      source_flow: record.source_flow,\n      _meta: {\n        source: source,\n        detected_format: source,\n        processed_at: new Date().toISOString()\n      }\n    }\n  }];\n}\n\n// No valid record found - log and skip\nconsole.log('Transform: No valid event format detected', JSON.stringify(input).substring(0, 500));\nreturn [];"},"id":"b765d6be-4447-4693-a4c9-4400c4e4ac43","name":"Transform Webhook Payload","type":"n8n-nodes-base.code","typeVersion":2,"position":[-1424,400],"notes":"Normalizes Supabase webhook payload to match sweeper format"},{"parameters":{"operation":"executeQuery","query":"SELECT \n  e.id,\n  e.project_id,\n  e.event_type::TEXT as event_type,\n  e.payload,\n  e.created_at,\n  e.source_system,\n  e.source_flow,\n  r.target_workflow,\n  r.webhook_url\nFROM events e\nJOIN event_routing r ON e.event_type::TEXT = r.event_type\nWHERE e.processed_at IS NULL\n  AND r.is_active = true\n  AND e.created_at < now() - INTERVAL '2 minutes'\nORDER BY e.created_at ASC\nLIMIT 50;","options":{}},"type":"n8n-nodes-base.postgres","typeVersion":2.6,"position":[-1424,624],"id":"09bf4366-a9b0-446f-8622-157e62a7a64a","name":"Fetch Unprocessed Events","credentials":{"postgres":{"id":"qXZ2ZjK31ZDrPoDG","name":"Supabase Postgres"}},"notes":"Sweeper: Fetches events older than 2 minutes that haven't been processed"},{"parameters":{"operation":"executeQuery","query":"SELECT \n  target_workflow,\n  webhook_url\nFROM event_routing\nWHERE event_type = '{{ $('Transform Webhook Payload').item.json.event_type }}'\n  AND is_active = true;","options":{}},"type":"n8n-nodes-base.postgres","typeVersion":2.6,"position":[-1216,400],"id":"d5ebb710-04f2-4965-b730-3ac0e566ae7c","name":"Lookup Routing","credentials":{"postgres":{"id":"qXZ2ZjK31ZDrPoDG","name":"Supabase Postgres"}},"notes":"Looks up target workflow from event_routing table"},{"parameters":{"jsCode":"// Merge event with ALL routes (multi-route support)\nconst event = $('Transform Webhook Payload').first().json;\nconst routes = $input.all();\n\nif (routes.length === 0) {\n  return [{ json: { ...event, target_workflow: null, webhook_url: null, source: 'webhook' } }];\n}\n\nreturn routes.map(route => ({\n  json: {\n    ...event,\n    target_workflow: route.json.target_workflow,\n    webhook_url: route.json.webhook_url,\n    source: 'webhook'\n  }\n}));"},"id":"324bb688-1c73-46e1-b8d3-f48672bb78d5","name":"Merge Routing Info","type":"n8n-nodes-base.code","typeVersion":2,"position":[-1024,400],"notes":"Combines event with its routing destination"},{"parameters":{"jsCode":"// Add source marker to sweeper items\nconst items = $input.all();\nreturn items.map(item => ({\n  json: {\n    ...item.json,\n    source: 'sweeper'\n  }\n}));"},"id":"803b1fb4-7afe-46c8-b7a9-0c696a424fb3","name":"Mark as Sweeper","type":"n8n-nodes-base.code","typeVersion":2,"position":[-1216,624],"notes":"Marks items from sweeper path for debugging"},{"parameters":{},"id":"c6c69f71-ae7f-4137-9cd1-3c5d9292b4c9","name":"Merge Both Paths","type":"n8n-nodes-base.merge","typeVersion":3,"position":[-784,512],"notes":"Combines webhook and sweeper paths into single stream"},{"parameters":{"conditions":{"options":{"caseSensitive":true,"leftValue":"","typeValidation":"strict","version":2},"conditions":[{"id":"has-routing","leftValue":"={{ $json.webhook_url }}","rightValue":"","operator":{"type":"string","operation":"notEmpty"}}],"combinator":"and"},"options":{}},"id":"73fb528f-9f90-48dc-a160-e3030dd13bfb","name":"Has Routing?","type":"n8n-nodes-base.filter","typeVersion":2,"position":[-592,512],"notes":"Only process events that have a webhook_url configured"},{"parameters":{"operation":"executeQuery","query":"UPDATE events \nSET processed_at = now() \nWHERE id = '{{ $json.id }}'::uuid\n  AND processed_at IS NULL\nRETURNING id, event_type::text, processed_at;","options":{}},"type":"n8n-nodes-base.postgres","typeVersion":2.6,"position":[-224,512],"id":"ec8ec304-e9f3-4409-a59f-a60fd6921615","name":"Mark as Processed","credentials":{"postgres":{"id":"qXZ2ZjK31ZDrPoDG","name":"Supabase Postgres"}},"notes":"Marks the event as processed to prevent re-processing"},{"parameters":{"jsCode":"// Final output\nconst items = $input.all();\n\nreturn items.map(item => ({\n  json: {\n    status: item.json.dispatch_status || 'processed',\n    event_id: item.json.id,\n    event_type: item.json.event_type,\n    target_workflow: item.json.target_workflow,\n    processed_at: item.json.processed_at\n  }\n}));"},"id":"05ff87e5-03ae-42a4-88cb-836d9f67b902","name":"Done","type":"n8n-nodes-base.code","typeVersion":2,"position":[-64,512],"notes":"Final output node"},{"parameters":{"jsCode":"// Dynamic Route Dispatcher v2\n// Dispatches to ALL routes, returns errors as separate items for DB logging\n\nconst items = $input.all();\nconst results = [];\n\nfor (const item of items) {\n  const event = item.json;\n  const webhookUrl = event.webhook_url;\n  const targetWorkflow = event.target_workflow;\n  \n  if (!webhookUrl) {\n    console.log('⏭️ Skipping - no webhook_url for:', event.event_type);\n    continue;\n  }\n  \n  const payload = {\n    event_id: event.id,\n    event_type: event.event_type,\n    project_id: event.project_id,\n    payload: event.payload\n  };\n  \n  try {\n    const response = await this.helpers.httpRequest({\n      method: 'POST',\n      url: webhookUrl,\n      body: payload,\n      json: true,\n      timeout: 120000\n    });\n    \n    results.push({\n      json: {\n        ...event,\n        dispatch_status: 'success',\n        _isError: false\n      }\n    });\n    \n    console.log(`✅ Dispatched to ${targetWorkflow}`);\n    \n  } catch (error) {\n    const errorCode = error.code || 'UNKNOWN';\n    const httpStatus = error.response?.status || null;\n    \n    results.push({\n      json: {\n        ...event,\n        dispatch_status: 'error',\n        _isError: true,\n        _error: {\n          event_id: event.id,\n          event_type: event.event_type,\n          target_workflow: targetWorkflow,\n          webhook_url: webhookUrl,\n          error_message: error.message,\n          error_code: errorCode,\n          http_status: httpStatus\n        }\n      }\n    });\n    \n    console.error(`❌ Error dispatching to ${targetWorkflow}:`, error.message);\n  }\n}\n\nreturn results.length > 0 ? results : [{ json: { status: 'no_routes_dispatched', _isError: false } }];"},"type":"n8n-nodes-base.code","typeVersion":2,"position":[-416,512],"id":"f6647989-6bce-4dd7-9162-d468950082d1","name":"Dynamic Route Dispatcher"},{"parameters":{"conditions":{"options":{"caseSensitive":true,"leftValue":"","typeValidation":"strict","version":3},"conditions":[{"id":"4189fca4-48e7-4eb0-a327-4e76ff42a766","leftValue":"={{ $json._isError }}","rightValue":"","operator":{"type":"boolean","operation":"true","singleValue":true}}],"combinator":"and"},"options":{}},"type":"n8n-nodes-base.filter","typeVersion":2.3,"position":[-224,336],"id":"3571da9c-1dab-4593-9012-da4f3572383f","name":"Has Errors?"},{"parameters":{"operation":"executeQuery","query":"INSERT INTO dispatch_errors (\n  event_id,\n  event_type,\n  target_workflow,\n  webhook_url,\n  error_message,\n  error_code\n) VALUES (\n  NULLIF('{{ $json._error.event_id }}', '')::uuid,\n  '{{ $json._error.event_type }}',\n  '{{ $json._error.target_workflow }}',\n  '{{ $json._error.webhook_url }}',\n  '{{ $json._error.error_message }}',\n  '{{ $json._error.error_code }}'\n)\nRETURNING id;","options":{}},"type":"n8n-nodes-base.postgres","typeVersion":2.6,"position":[-64,336],"id":"b3893837-e399-4a95-9053-6f16fafc2a89","name":"Log Dispatch Error","credentials":{"postgres":{"id":"qXZ2ZjK31ZDrPoDG","name":"Supabase Postgres"}}}],"connections":{"Webhook Trigger":{"main":[[{"node":"Transform Webhook Payload","type":"main","index":0}]]},"Sweeper Trigger":{"main":[[{"node":"Fetch Unprocessed Events","type":"main","index":0}]]},"Transform Webhook Payload":{"main":[[{"node":"Lookup Routing","type":"main","index":0}]]},"Fetch Unprocessed Events":{"main":[[{"node":"Mark as Sweeper","type":"main","index":0}]]},"Lookup Routing":{"main":[[{"node":"Merge Routing Info","type":"main","index":0}]]},"Merge Routing Info":{"main":[[{"node":"Merge Both Paths","type":"main","index":0}]]},"Mark as Sweeper":{"main":[[{"node":"Merge Both Paths","type":"main","index":1}]]},"Merge Both Paths":{"main":[[{"node":"Has Routing?","type":"main","index":0}]]},"Has Routing?":{"main":[[{"node":"Dynamic Route Dispatcher","type":"main","index":0}]]},"Mark as Processed":{"main":[[{"node":"Done","type":"main","index":0}]]},"Dynamic Route Dispatcher":{"main":[[{"node":"Has Errors?","type":"main","index":0},{"node":"Mark as Processed","type":"main","index":0}]]},"Has Errors?":{"main":[[{"node":"Log Dispatch Error","type":"main","index":0}]]}},"settings":{"executionOrder":"v1","availableInMCP":false,"timeSavedMode":"fixed","callerPolicy":"workflowsFromSameOwner","errorWorkflow":"apmJoMCbOchwfqTp"},"staticData":{"node:Sweeper Trigger":{"recurrenceRules":[]}},"meta":{"templateCredsSetupCompleted":true},"pinData":{"Webhook Trigger":[{"json":{"headers":{},"query":{},"body":{"type":"INSERT","table":"events","record":{"id":"e5f6a7b8-c9d0-1234-ef01-567890123456","payload":{"test":true,"protocol_id":"error-test-final"},"event_type":"INSPECTION_PROTOCOL_COMPLETED","project_id":null}}},"pairedItem":{"item":0}}]},"versionId":"69d7e552-baf8-4dd2-8603-3b977fe51fae","activeVersionId":"69d7e552-baf8-4dd2-8603-3b977fe51fae","versionCounter":45,"triggerCount":2,"shared":[{"updatedAt":"2026-01-17T17:34:57.290Z","createdAt":"2026-01-17T17:34:57.290Z","role":"workflow:owner","workflowId":"eNHx0TACVcF6MIdAYIKSl","projectId":"lxYwL2wy7xgg1POq","project":{"updatedAt":"2025-10-10T16:06:01.650Z","createdAt":"2025-10-04T22:17:46.741Z","id":"lxYwL2wy7xgg1POq","name":"Dennis Özdemir <info@deine-bauloewen.de>","type":"personal","icon":null,"description":null,"creatorId":"f290b8bc-a990-495d-aedc-d1ee5abfc443"}}],"tags":[],"activeVersion":{"updatedAt":"2026-03-08T11:35:22.821Z","createdAt":"2026-03-08T11:35:22.821Z","versionId":"69d7e552-baf8-4dd2-8603-3b977fe51fae","workflowId":"eNHx0TACVcF6MIdAYIKSl","nodes":[{"parameters":{"httpMethod":"POST","path":"event-router","options":{}},"id":"c8003aa5-c127-4938-bde8-a37bb758fe35","name":"Webhook Trigger","type":"n8n-nodes-base.webhook","typeVersion":2,"position":[-1616,400],"webhookId":"event-router","notes":"Receives POST from Supabase Database Webhook on INSERT to events table"},{"parameters":{"rule":{"interval":[{"field":"minutes"}]}},"id":"f6a07c43-13b1-4cf6-a26e-16b460529dd2","name":"Sweeper Trigger","type":"n8n-nodes-base.scheduleTrigger","typeVersion":1.2,"position":[-1616,624],"notes":"Runs every 5 minutes to catch missed events (Belt & Suspenders)"},{"parameters":{"jsCode":"// Transform Webhook Payload - V2 (Multi-Format Support)\n// Unterstützt: Supabase Webhook, Direct POST, curl, n8n HTTP Request\n\nconst input = $input.first().json;\nlet record = null;\nlet source = 'webhook';\n\n// ============================================\n// FORMAT 1: Supabase Database Webhook\n// Struktur: { type: 'INSERT', table: 'events', record: {...} }\n// ============================================\nif (input.type === 'INSERT' && input.record) {\n  record = input.record;\n  source = 'supabase_webhook';\n}\n\n// ============================================\n// FORMAT 2: Direct POST (curl, Postman, andere Flows)\n// Struktur: { event_id, event_type, project_id, payload }\n// ============================================\nelse if (input.event_id && input.event_type) {\n  record = {\n    id: input.event_id,\n    event_type: input.event_type,\n    project_id: input.project_id,\n    payload: input.payload || {},\n    created_at: input.created_at || new Date().toISOString(),\n    source_system: input.source_system || 'manual',\n    source_flow: input.source_flow || 'direct_post'\n  };\n  source = 'direct_post';\n}\n\n// ============================================\n// FORMAT 3: n8n Webhook Body Wrapper\n// Struktur: { body: { event_id, event_type, ... } }\n// ============================================\nelse if (input.body?.event_id && input.body?.event_type) {\n  record = {\n    id: input.body.event_id,\n    event_type: input.body.event_type,\n    project_id: input.body.project_id,\n    payload: input.body.payload || {},\n    created_at: input.body.created_at || new Date().toISOString(),\n    source_system: input.body.source_system || 'n8n',\n    source_flow: input.body.source_flow || 'webhook_body'\n  };\n  source = 'webhook_body';\n}\n\n// ============================================\n// FORMAT 4: Supabase Webhook wrapped in body\n// Struktur: { body: { type: 'INSERT', record: {...} } }\n// ============================================\nelse if (input.body?.type === 'INSERT' && input.body?.record) {\n  record = input.body.record;\n  source = 'supabase_webhook_wrapped';\n}\n\n// ============================================\n// FORMAT 5: Event-Objekt direkt (von Sweeper oder anderem Flow)\n// Struktur: { id, event_type, project_id, payload, ... }\n// ============================================\nelse if (input.id && input.event_type) {\n  record = {\n    id: input.id,\n    event_type: input.event_type,\n    project_id: input.project_id,\n    payload: input.payload || {},\n    created_at: input.created_at,\n    source_system: input.source_system,\n    source_flow: input.source_flow\n  };\n  source = 'event_object';\n}\n\n// ============================================\n// OUTPUT\n// ============================================\nif (record && record.event_type) {\n  return [{\n    json: {\n      id: record.id,\n      event_type: String(record.event_type), // Ensure string for Switch\n      project_id: record.project_id,\n      payload: typeof record.payload === 'string' \n        ? JSON.parse(record.payload) \n        : (record.payload || {}),\n      created_at: record.created_at,\n      source_system: record.source_system,\n      source_flow: record.source_flow,\n      _meta: {\n        source: source,\n        detected_format: source,\n        processed_at: new Date().toISOString()\n      }\n    }\n  }];\n}\n\n// No valid record found - log and skip\nconsole.log('Transform: No valid event format detected', JSON.stringify(input).substring(0, 500));\nreturn [];"},"id":"b765d6be-4447-4693-a4c9-4400c4e4ac43","name":"Transform Webhook Payload","type":"n8n-nodes-base.code","typeVersion":2,"position":[-1424,400],"notes":"Normalizes Supabase webhook payload to match sweeper format"},{"parameters":{"operation":"executeQuery","query":"SELECT \n  e.id,\n  e.project_id,\n  e.event_type::TEXT as event_type,\n  e.payload,\n  e.created_at,\n  e.source_system,\n  e.source_flow,\n  r.target_workflow,\n  r.webhook_url\nFROM events e\nJOIN event_routing r ON e.event_type::TEXT = r.event_type\nWHERE e.processed_at IS NULL\n  AND r.is_active = true\n  AND e.created_at < now() - INTERVAL '2 minutes'\nORDER BY e.created_at ASC\nLIMIT 50;","options":{}},"type":"n8n-nodes-base.postgres","typeVersion":2.6,"position":[-1424,624],"id":"09bf4366-a9b0-446f-8622-157e62a7a64a","name":"Fetch Unprocessed Events","credentials":{"postgres":{"id":"qXZ2ZjK31ZDrPoDG","name":"Supabase Postgres"}},"notes":"Sweeper: Fetches events older than 2 minutes that haven't been processed"},{"parameters":{"operation":"executeQuery","query":"SELECT \n  target_workflow,\n  webhook_url\nFROM event_routing\nWHERE event_type = '{{ $('Transform Webhook Payload').item.json.event_type }}'\n  AND is_active = true;","options":{}},"type":"n8n-nodes-base.postgres","typeVersion":2.6,"position":[-1216,400],"id":"d5ebb710-04f2-4965-b730-3ac0e566ae7c","name":"Lookup Routing","credentials":{"postgres":{"id":"qXZ2ZjK31ZDrPoDG","name":"Supabase Postgres"}},"notes":"Looks up target workflow from event_routing table"},{"parameters":{"jsCode":"// Merge event with ALL routes (multi-route support)\nconst event = $('Transform Webhook Payload').first().json;\nconst routes = $input.all();\n\nif (routes.length === 0) {\n  return [{ json: { ...event, target_workflow: null, webhook_url: null, source: 'webhook' } }];\n}\n\nreturn routes.map(route => ({\n  json: {\n    ...event,\n    target_workflow: route.json.target_workflow,\n    webhook_url: route.json.webhook_url,\n    source: 'webhook'\n  }\n}));"},"id":"324bb688-1c73-46e1-b8d3-f48672bb78d5","name":"Merge Routing Info","type":"n8n-nodes-base.code","typeVersion":2,"position":[-1024,400],"notes":"Combines event with its routing destination"},{"parameters":{"jsCode":"// Add source marker to sweeper items\nconst items = $input.all();\nreturn items.map(item => ({\n  json: {\n    ...item.json,\n    source: 'sweeper'\n  }\n}));"},"id":"803b1fb4-7afe-46c8-b7a9-0c696a424fb3","name":"Mark as Sweeper","type":"n8n-nodes-base.code","typeVersion":2,"position":[-1216,624],"notes":"Marks items from sweeper path for debugging"},{"parameters":{},"id":"c6c69f71-ae7f-4137-9cd1-3c5d9292b4c9","name":"Merge Both Paths","type":"n8n-nodes-base.merge","typeVersion":3,"position":[-784,512],"notes":"Combines webhook and sweeper paths into single stream"},{"parameters":{"conditions":{"options":{"caseSensitive":true,"leftValue":"","typeValidation":"strict","version":2},"conditions":[{"id":"has-routing","leftValue":"={{ $json.webhook_url }}","rightValue":"","operator":{"type":"string","operation":"notEmpty"}}],"combinator":"and"},"options":{}},"id":"73fb528f-9f90-48dc-a160-e3030dd13bfb","name":"Has Routing?","type":"n8n-nodes-base.filter","typeVersion":2,"position":[-592,512],"notes":"Only process events that have a webhook_url configured"},{"parameters":{"operation":"executeQuery","query":"UPDATE events \nSET processed_at = now() \nWHERE id = '{{ $json.id }}'::uuid\n  AND processed_at IS NULL\nRETURNING id, event_type::text, processed_at;","options":{}},"type":"n8n-nodes-base.postgres","typeVersion":2.6,"position":[-224,512],"id":"ec8ec304-e9f3-4409-a59f-a60fd6921615","name":"Mark as Processed","credentials":{"postgres":{"id":"qXZ2ZjK31ZDrPoDG","name":"Supabase Postgres"}},"notes":"Marks the event as processed to prevent re-processing"},{"parameters":{"jsCode":"// Final output\nconst items = $input.all();\n\nreturn items.map(item => ({\n  json: {\n    status: item.json.dispatch_status || 'processed',\n    event_id: item.json.id,\n    event_type: item.json.event_type,\n    target_workflow: item.json.target_workflow,\n    processed_at: item.json.processed_at\n  }\n}));"},"id":"05ff87e5-03ae-42a4-88cb-836d9f67b902","name":"Done","type":"n8n-nodes-base.code","typeVersion":2,"position":[-64,512],"notes":"Final output node"},{"parameters":{"jsCode":"// Dynamic Route Dispatcher v2\n// Dispatches to ALL routes, returns errors as separate items for DB logging\n\nconst items = $input.all();\nconst results = [];\n\nfor (const item of items) {\n  const event = item.json;\n  const webhookUrl = event.webhook_url;\n  const targetWorkflow = event.target_workflow;\n  \n  if (!webhookUrl) {\n    console.log('⏭️ Skipping - no webhook_url for:', event.event_type);\n    continue;\n  }\n  \n  const payload = {\n    event_id: event.id,\n    event_type: event.event_type,\n    project_id: event.project_id,\n    payload: event.payload\n  };\n  \n  try {\n    const response = await this.helpers.httpRequest({\n      method: 'POST',\n      url: webhookUrl,\n      body: payload,\n      json: true,\n      timeout: 120000\n    });\n    \n    results.push({\n      json: {\n        ...event,\n        dispatch_status: 'success',\n        _isError: false\n      }\n    });\n    \n    console.log(`✅ Dispatched to ${targetWorkflow}`);\n    \n  } catch (error) {\n    const errorCode = error.code || 'UNKNOWN';\n    const httpStatus = error.response?.status || null;\n    \n    results.push({\n      json: {\n        ...event,\n        dispatch_status: 'error',\n        _isError: true,\n        _error: {\n          event_id: event.id,\n          event_type: event.event_type,\n          target_workflow: targetWorkflow,\n          webhook_url: webhookUrl,\n          error_message: error.message,\n          error_code: errorCode,\n          http_status: httpStatus\n        }\n      }\n    });\n    \n    console.error(`❌ Error dispatching to ${targetWorkflow}:`, error.message);\n  }\n}\n\nreturn results.length > 0 ? results : [{ json: { status: 'no_routes_dispatched', _isError: false } }];"},"type":"n8n-nodes-base.code","typeVersion":2,"position":[-416,512],"id":"f6647989-6bce-4dd7-9162-d468950082d1","name":"Dynamic Route Dispatcher"},{"parameters":{"conditions":{"options":{"caseSensitive":true,"leftValue":"","typeValidation":"strict","version":3},"conditions":[{"id":"4189fca4-48e7-4eb0-a327-4e76ff42a766","leftValue":"={{ $json._isError }}","rightValue":"","operator":{"type":"boolean","operation":"true","singleValue":true}}],"combinator":"and"},"options":{}},"type":"n8n-nodes-base.filter","typeVersion":2.3,"position":[-224,336],"id":"3571da9c-1dab-4593-9012-da4f3572383f","name":"Has Errors?"},{"parameters":{"operation":"executeQuery","query":"INSERT INTO dispatch_errors (\n  event_id,\n  event_type,\n  target_workflow,\n  webhook_url,\n  error_message,\n  error_code\n) VALUES (\n  NULLIF('{{ $json._error.event_id }}', '')::uuid,\n  '{{ $json._error.event_type }}',\n  '{{ $json._error.target_workflow }}',\n  '{{ $json._error.webhook_url }}',\n  '{{ $json._error.error_message }}',\n  '{{ $json._error.error_code }}'\n)\nRETURNING id;","options":{}},"type":"n8n-nodes-base.postgres","typeVersion":2.6,"position":[-64,336],"id":"b3893837-e399-4a95-9053-6f16fafc2a89","name":"Log Dispatch Error","credentials":{"postgres":{"id":"qXZ2ZjK31ZDrPoDG","name":"Supabase Postgres"}}}],"connections":{"Webhook Trigger":{"main":[[{"node":"Transform Webhook Payload","type":"main","index":0}]]},"Sweeper Trigger":{"main":[[{"node":"Fetch Unprocessed Events","type":"main","index":0}]]},"Transform Webhook Payload":{"main":[[{"node":"Lookup Routing","type":"main","index":0}]]},"Fetch Unprocessed Events":{"main":[[{"node":"Mark as Sweeper","type":"main","index":0}]]},"Lookup Routing":{"main":[[{"node":"Merge Routing Info","type":"main","index":0}]]},"Merge Routing Info":{"main":[[{"node":"Merge Both Paths","type":"main","index":0}]]},"Mark as Sweeper":{"main":[[{"node":"Merge Both Paths","type":"main","index":1}]]},"Merge Both Paths":{"main":[[{"node":"Has Routing?","type":"main","index":0}]]},"Has Routing?":{"main":[[{"node":"Dynamic Route Dispatcher","type":"main","index":0}]]},"Mark as Processed":{"main":[[{"node":"Done","type":"main","index":0}]]},"Dynamic Route Dispatcher":{"main":[[{"node":"Has Errors?","type":"main","index":0},{"node":"Mark as Processed","type":"main","index":0}]]},"Has Errors?":{"main":[[{"node":"Log Dispatch Error","type":"main","index":0}]]}},"authors":"Dennis Özdemir","name":null,"description":null,"autosaved":false,"workflowPublishHistory":[{"createdAt":"2026-03-08T11:35:22.923Z","id":977,"workflowId":"eNHx0TACVcF6MIdAYIKSl","versionId":"69d7e552-baf8-4dd2-8603-3b977fe51fae","event":"activated","userId":"f290b8bc-a990-495d-aedc-d1ee5abfc443"},{"createdAt":"2026-03-08T11:35:22.893Z","id":976,"workflowId":"eNHx0TACVcF6MIdAYIKSl","versionId":"69d7e552-baf8-4dd2-8603-3b977fe51fae","event":"deactivated","userId":"f290b8bc-a990-495d-aedc-d1ee5abfc443"}]}}